{
  "DLSVersion": "2.1.6",
  "Name": "Mem-8",
  "NameLocation": 0,
  "ChipType": 0,
  "Size": {
    "x": 0.875,
    "y": 0.75
  },
  "Colour": {
    "r": 0.241804287,
    "g": 0.029158365,
    "b": 0.06814752,
    "a": 1
  },
  "InputPins":[
    {
      "Name":"IN",
      "ID":101484186,
      "Position":{
        "x":-6.10833,
        "y":-0.15833
      },
      "BitCount":8,
      "Colour":0,
      "ValueDisplayMode":0
    },
    {
      "Name":"Write",
      "ID":1921694341,
      "Position":{
        "x":-5.61667,
        "y":-1.45
      },
      "BitCount":1,
      "Colour":0,
      "ValueDisplayMode":0
    }
  ],
  "OutputPins":[
    {
      "Name":"OUT",
      "ID":1437071360,
      "Position":{
        "x":3.01667,
        "y":-0.325
      },
      "BitCount":8,
      "Colour":0,
      "ValueDisplayMode":0
    }
  ],
  "SubChips":[
    {
      "Name":"8-4BIT",
      "ID":2125766046,
      "Label":"",
      "Position":{
        "x":-3.95,
        "y":-0.19167
      },
      "OutputPinColourInfo":[{"PinColour":0,"PinID":1},{"PinColour":0,"PinID":2}],
      "InternalData":null
    },
    {
      "Name":"4-8BIT",
      "ID":1635539300,
      "Label":"",
      "Position":{
        "x":0.775,
        "y":-0.36667
      },
      "OutputPinColourInfo":[{"PinColour":0,"PinID":2}],
      "InternalData":null
    },
    {
      "Name":"Mem-4",
      "ID":2101602095,
      "Label":"",
      "Position":{
        "x":-1.875,
        "y":0.19167
      },
      "OutputPinColourInfo":[{"PinColour":0,"PinID":1540301995}],
      "InternalData":null
    },
    {
      "Name":"Mem-4",
      "ID":98246654,
      "Label":"",
      "Position":{
        "x":-1.875,
        "y":-0.59167
      },
      "OutputPinColourInfo":[{"PinColour":0,"PinID":1540301995}],
      "InternalData":null
    }
  ],
  "Wires":[
    {
      "SourcePinAddress":{
        "PinID":0,
        "PinOwnerID":101484186
      },
      "TargetPinAddress":{
        "PinID":0,
        "PinOwnerID":2125766046
      },
      "ConnectionType":0,
      "ConnectedWireIndex":-1,
      "ConnectedWireSegmentIndex":-1,
      "Points":[{"x":0.0,"y":0.0},{"x":0.0,"y":0.0}]
    },
    {
      "SourcePinAddress":{
        "PinID":2,
        "PinOwnerID":1635539300
      },
      "TargetPinAddress":{
        "PinID":0,
        "PinOwnerID":1437071360
      },
      "ConnectionType":0,
      "ConnectedWireIndex":-1,
      "ConnectedWireSegmentIndex":-1,
      "Points":[{"x":0.0,"y":0.0},{"x":0.0,"y":0.0}]
    },
    {
      "SourcePinAddress":{
        "PinID":1,
        "PinOwnerID":2125766046
      },
      "TargetPinAddress":{
        "PinID":1453375287,
        "PinOwnerID":2101602095
      },
      "ConnectionType":0,
      "ConnectedWireIndex":-1,
      "ConnectedWireSegmentIndex":-1,
      "Points":[{"x":0.0,"y":0.0},{"x":0.0,"y":0.0}]
    },
    {
      "SourcePinAddress":{
        "PinID":2,
        "PinOwnerID":2125766046
      },
      "TargetPinAddress":{
        "PinID":1453375287,
        "PinOwnerID":98246654
      },
      "ConnectionType":0,
      "ConnectedWireIndex":-1,
      "ConnectedWireSegmentIndex":-1,
      "Points":[{"x":0.0,"y":0.0},{"x":0.0,"y":0.0}]
    },
    {
      "SourcePinAddress":{
        "PinID":1540301995,
        "PinOwnerID":2101602095
      },
      "TargetPinAddress":{
        "PinID":0,
        "PinOwnerID":1635539300
      },
      "ConnectionType":0,
      "ConnectedWireIndex":-1,
      "ConnectedWireSegmentIndex":-1,
      "Points":[{"x":0.0,"y":0.0},{"x":0.0,"y":0.0}]
    },
    {
      "SourcePinAddress":{
        "PinID":1540301995,
        "PinOwnerID":98246654
      },
      "TargetPinAddress":{
        "PinID":1,
        "PinOwnerID":1635539300
      },
      "ConnectionType":0,
      "ConnectedWireIndex":-1,
      "ConnectedWireSegmentIndex":-1,
      "Points":[{"x":0.0,"y":0.0},{"x":0.0,"y":0.0}]
    },
    {
      "SourcePinAddress":{
        "PinID":0,
        "PinOwnerID":1921694341
      },
      "TargetPinAddress":{
        "PinID":405762141,
        "PinOwnerID":2101602095
      },
      "ConnectionType":0,
      "ConnectedWireIndex":-1,
      "ConnectedWireSegmentIndex":-1,
      "Points":[{"x":0.0,"y":0.0},{"x":0.0,"y":0.0}]
    },
    {
      "SourcePinAddress":{
        "PinID":0,
        "PinOwnerID":1921694341
      },
      "TargetPinAddress":{
        "PinID":405762141,
        "PinOwnerID":98246654
      },
      "ConnectionType":0,
      "ConnectedWireIndex":-1,
      "ConnectedWireSegmentIndex":-1,
      "Points":[{"x":0.0,"y":0.0},{"x":0.0,"y":0.0}]
    }
  ],
  "Displays": null
}